drf_ip_restrictions/__init__.py
drf_ip_restrictions/permissions.py
drf_ip_restrictions/settings.py
drf_ip_restrictions-1.1.1.dist-info/LICENSE
drf_ip_restrictions-1.1.1.dist-info/METADATA
drf_ip_restrictions-1.1.1.dist-info/WHEEL
drf_ip_restrictions-1.1.1.dist-info/top_level.txt
drf_ip_restrictions-1.1.1.dist-info/RECORD
