Metadata-Version: 2.1
Name: drf-ip-restrictions
Version: 1.1.1
Summary: A library that allows IP restrictions for views/endpoints in Django REST framework.
Home-page: https://github.com/anexia/drf-ip-restrictions
Author: Alexandra Bruckner
Author-email: abruckner@anexia-it.com
License: MIT License
Platform: UNKNOWN
Classifier: Development Status :: 5 - Production/Stable
Classifier: Framework :: Django
Classifier: Framework :: Django :: 3.2
Classifier: Intended Audience :: Developers
Classifier: License :: OSI Approved :: MIT License
Classifier: Operating System :: OS Independent
Classifier: Programming Language :: Python
Classifier: Programming Language :: Python :: 3
Classifier: Programming Language :: Python :: 3.7
Classifier: Programming Language :: Python :: 3.8
Classifier: Programming Language :: Python :: 3.9
Classifier: Programming Language :: Python :: 3.10
Requires-Dist: django (>=3.2)
Requires-Dist: djangorestframework (>=3.12)
Requires-Dist: django-ipware (>=4.0.2)
